ms_marathon_api/__init__.py
ms_marathon_api/marathon/__init__.py
ms_marathon_api/marathon/__tests__/__init__.py
ms_marathon_api/marathon/api/__init__.py
ms_marathon_api/marathon/api/__tests__/__init__.py
ms_marathon_api/marathon/api/__tests__/test_timereporting.py
ms_marathon_api/marathon/api/timereporting.py
ms_marathon_api/marathon/connection/__init__.py
ms_marathon_api/marathon/connection/__tests__/__init__.py
ms_marathon_api/marathon/connection/__tests__/test_mysql_connection.py
ms_marathon_api/marathon/connection/mysql.py
ms_marathon_api/marathon/dto/TimeReportingDTO.py
ms_marathon_api/marathon/dto/__init__.py
ms_marathon_api/marathon/queries/__init__.py
ms_marathon_api/marathon/queries/marathon.py
ms_marathon_api-0.2.0.dist-info/LICENSE
ms_marathon_api-0.2.0.dist-info/METADATA
ms_marathon_api-0.2.0.dist-info/WHEEL
ms_marathon_api-0.2.0.dist-info/RECORD
