Metadata-Version: 2.1
Name: ms-marathon-api
Version: 0.2.0
Summary: API to connect with Marathon system and migrate data to Bigquery
Author: Making Science
Requires-Python: >=3.8.1,<4.0.0
Classifier: Programming Language :: Python :: 3
Classifier: Programming Language :: Python :: 3.9
Classifier: Programming Language :: Python :: 3.10
Classifier: Programming Language :: Python :: 3.11
Requires-Dist: coverage (>=7.2.2,<8.0.0)
Requires-Dist: flake8 (>=6.0.0,<7.0.0)
Requires-Dist: gc-google-services-api (>=1.3.0,<2.0.0)
Requires-Dist: isort (>=5.12.0,<6.0.0)
Requires-Dist: mysql-connector-python (>=8.0.33,<9.0.0)
Requires-Dist: pre-commit (>=3.1.1,<4.0.0)
